reagex/__init__.py
reagex/reagex.py
reagex-0.1.2.dist-info/AUTHORS.rst
reagex-0.1.2.dist-info/LICENSE
reagex-0.1.2.dist-info/METADATA
reagex-0.1.2.dist-info/WHEEL
reagex-0.1.2.dist-info/top_level.txt
reagex-0.1.2.dist-info/RECORD
