Metadata-Version: 2.1
Name: reagex
Version: 0.1.2
Summary: Utility functions for writing readable regular expressions in a hierarchical way
Home-page: https://github.com/janluke/python-reagex
Author: Gianluca Gippetto
Author-email: gianluca.gippetto@gmail.com
License: BSD 2-Clause License
Keywords: regular-expression,regex,pattern,readable,readability
Platform: UNKNOWN
Classifier: Intended Audience :: Developers
Classifier: License :: OSI Approved :: BSD License
Classifier: Operating System :: Unix
Classifier: Operating System :: POSIX
Classifier: Operating System :: Microsoft :: Windows
Classifier: Programming Language :: Python
Classifier: Programming Language :: Python :: 2.7
Classifier: Programming Language :: Python :: 3
Classifier: Programming Language :: Python :: 3.4
Classifier: Programming Language :: Python :: 3.5
Classifier: Programming Language :: Python :: 3.6
Classifier: Programming Language :: Python :: 3.7
Classifier: Programming Language :: Python :: Implementation :: CPython
Classifier: Programming Language :: Python :: Implementation :: PyPy
Classifier: Topic :: Utilities
